avrcp_volume/__init__.py
avrcp_volume/avrcp_controller.py
avrcp_volume/installer.py
avrcp_volume/logger.py
avrcp_volume/message_bus.py
avrcp_volume/pulse/__init__.py
avrcp_volume/pulse/pa_controller.py
avrcp_volume/pulse/sink.py
avrcp_volume/resources/avrcp-volume.service
avrcp_volume-0.7.5.dist-info/LICENSE
avrcp_volume-0.7.5.dist-info/METADATA
avrcp_volume-0.7.5.dist-info/WHEEL
avrcp_volume-0.7.5.dist-info/entry_points.txt
avrcp_volume-0.7.5.dist-info/top_level.txt
avrcp_volume-0.7.5.dist-info/RECORD
