Metadata-Version: 2.1
Name: avrcp-volume
Version: 0.7.5
Summary: Avrcp volume controller
Home-page: https://gitlab.com/hxss-linux/avrcp-volume
Author: hxss
Author-email: hxss@ya.ru
License: UNKNOWN
Platform: UNKNOWN
Classifier: Programming Language :: Python :: 3.8
Classifier: License :: OSI Approved :: MIT License
Classifier: Operating System :: POSIX :: Linux
Classifier: Topic :: Utilities
Requires-Python: >=3.8
Requires-Dist: dbus-next (>=0.1.3)
Requires-Dist: desktop-notify (>=1.2.1)
Requires-Dist: pulsectl (>=20.4.3)
